fb4/__init__.py
fb4/app.py
fb4/fb4common_bp.py
fb4/icons_bp.py
fb4/login_bp.py
fb4/sqldb.py
fb4/sse_bp.py
fb4/widgets.py
fb4/templates/fb4common/base.html
fb4/templates/fb4common/macros.html
fb4/templates/sse/sse.html
pyFlaskBootstrap4-0.6.1.dist-info/LICENSE
pyFlaskBootstrap4-0.6.1.dist-info/METADATA
pyFlaskBootstrap4-0.6.1.dist-info/WHEEL
pyFlaskBootstrap4-0.6.1.dist-info/top_level.txt
pyFlaskBootstrap4-0.6.1.dist-info/RECORD
