Metadata-Version: 2.1
Name: pyFlaskBootstrap4
Version: 0.6.1
Summary: python flask + Bootstrap 4 static components and templates for webprojects
Home-page: https://github.com/WolfgangFahl/pyFlaskBootstrap4
Download-URL: https://github.com/WolfgangFahl/pyFlaskBootstrap4
Author: Wolfgang Fahl
Author-email: wf@bitplan.com
License: Apache
Project-URL: Documentation, http://wiki.bitplan.com/index.php/pyFlaskBootstrap4
Project-URL: Code, https://github.com/WolfgangFahl/pyFlaskBootstrap4
Project-URL: Issue tracker, https://github.com/WolfgangFahl/pyFlaskBootstrap4/issues
Classifier: Programming Language :: Python
Classifier: Programming Language :: Python :: 3.8
Classifier: Programming Language :: Python :: 3.9
Classifier: Programming Language :: Python :: 3.10
Classifier: Programming Language :: Python :: 3.11
License-File: LICENSE
Requires-Dist: Bootstrap-Flask (>=1.8.0)
Requires-Dist: Flask-Dropzone (>=1.6.0)
Requires-Dist: Flask (>=2.0.2)
Requires-Dist: Flask-HTTPAuth (>=4.5.0)
Requires-Dist: Flask-Login (>=0.6.2)
Requires-Dist: Flask-SQLAlchemy (>=3.0.2)
Requires-Dist: Flask-WTF (>=1.0.0)
Requires-Dist: WTForms (>=3.0.0)
Requires-Dist: SQLAlchemy-Utils
Requires-Dist: requests
Requires-Dist: pydevd
Requires-Dist: pyDispatcher
Requires-Dist: APScheduler (>=3.9.1)
